gameboy/__init__.py
gameboy/__main__.py
gameboy/gameboy.py
gameboy/version.py
gameboy/common/__init__.py
gameboy/common/exception.py
gameboy/common/font.py
gameboy/common/loggings.py
gameboy/common/operation.py
gameboy/core/__init__.py
gameboy/core/event.py
gameboy/core/instruction.py
gameboy/core/interrupt.py
gameboy/hardware/__init__.py
gameboy/hardware/bus.py
gameboy/hardware/cartridge.py
gameboy/hardware/io.py
gameboy/hardware/lcd.py
gameboy/hardware/motherboard.py
gameboy/hardware/ppu.py
gameboy/hardware/ram.py
gameboy/hardware/timer.py
gameboy/hardware/cpu/__init__.py
gameboy/hardware/cpu/cpu.py
gameboy/hardware/cpu/execute.py
gameboy/hardware/cpu/util.py
gameboy/plugin/__init__.py
gameboy/plugin/base.py
gameboy/plugin/debugging.py
gameboy/plugin/window.py
gameboy_python-0.1.0.dist-info/LICENSE
gameboy_python-0.1.0.dist-info/METADATA
gameboy_python-0.1.0.dist-info/WHEEL
gameboy_python-0.1.0.dist-info/top_level.txt
gameboy_python-0.1.0.dist-info/RECORD
