Metadata-Version: 2.1
Name: gameboy-python
Version: 0.1.0
Summary: Game Boy Emulator in Python
Home-page: https://github.com/LittleNyima/gameboy-in-python
Author: LittleNyima
Author-email: littlenyima@163.com
License: GPLv3
Classifier: License :: OSI Approved :: GNU General Public License v3 (GPLv3)
Classifier: Operating System :: OS Independent
Classifier: Programming Language :: Python :: 3
License-File: LICENSE
